[
  {
    "id": "803722",
    "name": "ROCKET",
    "ca": "3o7gK8vZQV9rjPAtSVRMLPjh4xMs7MHfrcnyqxorpump",
    "channel": "MomentumTrackerCN",
    "timestamp": 1765270430.0,
    "mcap": "31.35K",
    "mentions": "2",
    "time_since_open": "\u6682\u65e0"
  },
  {
    "id": "803723",
    "name": "ROCKET",
    "ca": "3o7gK8vZQV9rjPAtSVRMLPjh4xMs7MHfrcnyqxorpump",
    "channel": "MomentumTrackerCN",
    "timestamp": 1765270449.0,
    "mcap": "36.10K",
    "mentions": "3",
    "time_since_open": "\u6682\u65e0"
  },
  {
    "id": "803724",
    "name": "DONALD",
    "ca": "Bi1WGxZBEn3FZ1eYdxqutX5iSrK5MaVQg8wqyhnrpump",
    "channel": "MomentumTrackerCN",
    "timestamp": 1765270456.0,
    "mcap": "32.00K",
    "mentions": "2",
    "time_since_open": "\u6682\u65e0"
  },
  {
    "id": "803725",
    "name": "DONALD",
    "ca": "Bi1WGxZBEn3FZ1eYdxqutX5iSrK5MaVQg8wqyhnrpump",
    "channel": "MomentumTrackerCN",
    "timestamp": 1765270479.0,
    "mcap": "33.41K",
    "mentions": "3",
    "time_since_open": "\u6682\u65e0"
  },
  {
    "id": "803726",
    "name": "RNUT",
    "ca": "BkEvgC9nfhy9TpCJDPUGy9ANXbYMxosfmLzk35gqpump",
    "channel": "MomentumTrackerCN",
    "timestamp": 1765270496.0,
    "mcap": "20.28K",
    "mentions": "2",
    "time_since_open": "\u6682\u65e0"
  },
  {
    "id": "803727",
    "name": "DONALD",
    "ca": "Bi1WGxZBEn3FZ1eYdxqutX5iSrK5MaVQg8wqyhnrpump",
    "channel": "MomentumTrackerCN",
    "timestamp": 1765270627.0,
    "mcap": "31.33K",
    "mentions": "4",
    "time_since_open": "\u6682\u65e0"
  },
  {
    "id": "803728",
    "name": "ACT",
    "ca": "nLu7QCUtvH6aLUb8RzkVgrB7FnUZNQrsAVeeLuLpump",
    "channel": "MomentumTrackerCN",
    "timestamp": 1765270627.0,
    "mcap": "87.32K",
    "mentions": "2",
    "time_since_open": "2\u520622\u79d2"
  },
  {
    "id": "803729",
    "name": "ROCKET",
    "ca": "3o7gK8vZQV9rjPAtSVRMLPjh4xMs7MHfrcnyqxorpump",
    "channel": "MomentumTrackerCN",
    "timestamp": 1765270707.0,
    "mcap": "49.82K",
    "mentions": "4",
    "time_since_open": "\u5c0f\u4e8e1\u5206\u949f"
  },
  {
    "id": "803730",
    "name": "ROCKET",
    "ca": "3o7gK8vZQV9rjPAtSVRMLPjh4xMs7MHfrcnyqxorpump",
    "channel": "MomentumTrackerCN",
    "timestamp": 1765270708.0,
    "mcap": "49.82K",
    "mentions": "5",
    "time_since_open": "6\u79d2"
  },
  {
    "id": "803731",
    "name": "ROCKET",
    "ca": "3o7gK8vZQV9rjPAtSVRMLPjh4xMs7MHfrcnyqxorpump",
    "channel": "MomentumTrackerCN",
    "timestamp": 1765270708.0,
    "mcap": "51.01K",
    "mentions": "6",
    "time_since_open": "6\u79d2"
  },
  {
    "id": "803732",
    "name": "WLC",
    "ca": "97jS5yH22prinVVRBEamgV669b6ZxgWwGka2AxRmpump",
    "channel": "MomentumTrackerCN",
    "timestamp": 1765270715.0,
    "mcap": "48.02K",
    "mentions": "4",
    "time_since_open": "5\u79d2"
  },
  {
    "id": "803733",
    "name": "WLC",
    "ca": "97jS5yH22prinVVRBEamgV669b6ZxgWwGka2AxRmpump",
    "channel": "MomentumTrackerCN",
    "timestamp": 1765270717.0,
    "mcap": "46.22K",
    "mentions": "5",
    "time_since_open": "5\u79d2"
  },
  {
    "id": "803737",
    "name": "ROCKET",
    "ca": "3o7gK8vZQV9rjPAtSVRMLPjh4xMs7MHfrcnyqxorpump",
    "channel": "MomentumTrackerCN",
    "timestamp": 1765271545.0,
    "mcap": "20.15K",
    "mentions": "7",
    "time_since_open": "6\u79d2"
  },
  {
    "id": "803738",
    "name": "WLC",
    "ca": "97jS5yH22prinVVRBEamgV669b6ZxgWwGka2AxRmpump",
    "channel": "MomentumTrackerCN",
    "timestamp": 1765271545.0,
    "mcap": "36.64K",
    "mentions": "6",
    "time_since_open": "5\u79d2"
  },
  {
    "id": "803739",
    "name": "WLC",
    "ca": "97jS5yH22prinVVRBEamgV669b6ZxgWwGka2AxRmpump",
    "channel": "MomentumTrackerCN",
    "timestamp": 1765271545.0,
    "mcap": "36.64K",
    "mentions": "7",
    "time_since_open": "5\u79d2"
  },
  {
    "id": "803740",
    "name": "BOLDLANA",
    "ca": "DduYjJgjsG1oAid8zYBR9JEN1tgSwm9QJNeCNQGZddXw",
    "channel": "MomentumTrackerCN",
    "timestamp": 1765271545.0,
    "mcap": "8.44K",
    "mentions": "1",
    "time_since_open": "\u6682\u65e0"
  },
  {
    "id": "803741",
    "name": "BOLDLANA",
    "ca": "DduYjJgjsG1oAid8zYBR9JEN1tgSwm9QJNeCNQGZddXw",
    "channel": "MomentumTrackerCN",
    "timestamp": 1765271546.0,
    "mcap": "8.29K",
    "mentions": "2",
    "time_since_open": "\u6682\u65e0"
  },
  {
    "id": "803742",
    "name": "SOLY",
    "ca": "8tAG6TzbZhFrHtQEm6XPkAcCuKYeNaEiKtAFuF1cpump",
    "channel": "MomentumTrackerCN",
    "timestamp": 1765271552.0,
    "mcap": "23.02K",
    "mentions": "1",
    "time_since_open": "\u6682\u65e0"
  },
  {
    "id": "803743",
    "name": "SOLY",
    "ca": "8tAG6TzbZhFrHtQEm6XPkAcCuKYeNaEiKtAFuF1cpump",
    "channel": "MomentumTrackerCN",
    "timestamp": 1765271552.0,
    "mcap": "23.04K",
    "mentions": "2",
    "time_since_open": "\u6682\u65e0"
  },
  {
    "id": "803744",
    "name": "USDT",
    "ca": "3Expf4KgPJ2tJHoz71jZmLP6RpSbW8bCMqiNH7oepump",
    "channel": "MomentumTrackerCN",
    "timestamp": 1765271552.0,
    "mcap": "104.95K",
    "mentions": "16",
    "time_since_open": "7\u79d2"
  },
  {
    "id": "803745",
    "name": "BOLDLANA",
    "ca": "DduYjJgjsG1oAid8zYBR9JEN1tgSwm9QJNeCNQGZddXw",
    "channel": "MomentumTrackerCN",
    "timestamp": 1765271552.0,
    "mcap": "8.77K",
    "mentions": "3",
    "time_since_open": "\u6682\u65e0"
  },
  {
    "id": "803746",
    "name": "ROCKET",
    "ca": "3o7gK8vZQV9rjPAtSVRMLPjh4xMs7MHfrcnyqxorpump",
    "channel": "MomentumTrackerCN",
    "timestamp": 1765271552.0,
    "mcap": "20.97K",
    "mentions": "8",
    "time_since_open": "6\u79d2"
  },
  {
    "id": "803747",
    "name": "TJ",
    "ca": "edRwir4HmmKV1PPSVSP4VVJnsAiR4vDTuFs2J42pump",
    "channel": "MomentumTrackerCN",
    "timestamp": 1765271568.0,
    "mcap": "233.70K",
    "mentions": "1",
    "time_since_open": "9\u52061\u79d2"
  },
  {
    "id": "803748",
    "name": "DONALD",
    "ca": "Bi1WGxZBEn3FZ1eYdxqutX5iSrK5MaVQg8wqyhnrpump",
    "channel": "MomentumTrackerCN",
    "timestamp": 1765271568.0,
    "mcap": "53.53K",
    "mentions": "8",
    "time_since_open": "5\u79d2"
  },
  {
    "id": "803680",
    "name": "SADGE",
    "ca": "8mCYtxU9bvXMvHwoBMjzUGSG9zAg4kgS1Bc5m4rVpump",
    "channel": "MomentumTrackerCN",
    "timestamp": 1765268911.0,
    "mcap": "52.68K",
    "mentions": "14",
    "time_since_open": "10\u79d2"
  },
  {
    "id": "803681",
    "name": "EVRO",
    "ca": "HPrF8Ba11X7FLHSqMRkeY8Snf9EZ3vT7eDbwzz41pump",
    "channel": "MomentumTrackerCN",
    "timestamp": 1765268911.0,
    "mcap": "27.09K",
    "mentions": "1",
    "time_since_open": "\u6682\u65e0"
  },
  {
    "id": "803682",
    "name": "USDT",
    "ca": "3Expf4KgPJ2tJHoz71jZmLP6RpSbW8bCMqiNH7oepump",
    "channel": "MomentumTrackerCN",
    "timestamp": 1765268911.0,
    "mcap": "75.96K",
    "mentions": "15",
    "time_since_open": "7\u79d2"
  },
  {
    "id": "803683",
    "name": "EVRO",
    "ca": "HPrF8Ba11X7FLHSqMRkeY8Snf9EZ3vT7eDbwzz41pump",
    "channel": "MomentumTrackerCN",
    "timestamp": 1765268923.0,
    "mcap": "28.28K",
    "mentions": "2",
    "time_since_open": "\u6682\u65e0"
  },
  {
    "id": "803684",
    "name": "EVRO",
    "ca": "HPrF8Ba11X7FLHSqMRkeY8Snf9EZ3vT7eDbwzz41pump",
    "channel": "MomentumTrackerCN",
    "timestamp": 1765268948.0,
    "mcap": "31.46K",
    "mentions": "3",
    "time_since_open": "\u6682\u65e0"
  },
  {
    "id": "803687",
    "name": "Gru",
    "ca": "5wfSeKwi6cmHu5XTKYUgbiZtUC7TNXqRsznBmTQ8pump",
    "channel": "MomentumTrackerCN",
    "timestamp": 1765269021.0,
    "mcap": "54.41K",
    "mentions": "2",
    "time_since_open": "10\u79d2"
  },
  {
    "id": "803688",
    "name": "Gru",
    "ca": "5wfSeKwi6cmHu5XTKYUgbiZtUC7TNXqRsznBmTQ8pump",
    "channel": "MomentumTrackerCN",
    "timestamp": 1765269032.0,
    "mcap": "48.19K",
    "mentions": "3",
    "time_since_open": "10\u79d2"
  },
  {
    "id": "803689",
    "name": "Gru",
    "ca": "5wfSeKwi6cmHu5XTKYUgbiZtUC7TNXqRsznBmTQ8pump",
    "channel": "MomentumTrackerCN",
    "timestamp": 1765269057.0,
    "mcap": "52.73K",
    "mentions": "4",
    "time_since_open": "10\u79d2"
  },
  {
    "id": "803690",
    "name": "Gru",
    "ca": "5wfSeKwi6cmHu5XTKYUgbiZtUC7TNXqRsznBmTQ8pump",
    "channel": "MomentumTrackerCN",
    "timestamp": 1765269183.0,
    "mcap": "62.78K",
    "mentions": "5",
    "time_since_open": "10\u79d2"
  },
  {
    "id": "803691",
    "name": "Gru",
    "ca": "5wfSeKwi6cmHu5XTKYUgbiZtUC7TNXqRsznBmTQ8pump",
    "channel": "MomentumTrackerCN",
    "timestamp": 1765269184.0,
    "mcap": "61.29K",
    "mentions": "5",
    "time_since_open": "10\u79d2"
  },
  {
    "id": "803693",
    "name": "Gru",
    "ca": "5wfSeKwi6cmHu5XTKYUgbiZtUC7TNXqRsznBmTQ8pump",
    "channel": "MomentumTrackerCN",
    "timestamp": 1765269190.0,
    "mcap": "59.21K",
    "mentions": "6",
    "time_since_open": "10\u79d2"
  },
  {
    "id": "803694",
    "name": "Gru",
    "ca": "5wfSeKwi6cmHu5XTKYUgbiZtUC7TNXqRsznBmTQ8pump",
    "channel": "MomentumTrackerCN",
    "timestamp": 1765269241.0,
    "mcap": "43.72K",
    "mentions": "7",
    "time_since_open": "10\u79d2"
  },
  {
    "id": "803695",
    "name": "DEUSVULTER",
    "ca": "67Mhw3r6Jo1wByEvY8ZN5KxmQiQDUwja3SYDDTZCpump",
    "channel": "MomentumTrackerCN",
    "timestamp": 1765269247.0,
    "mcap": "32.80K",
    "mentions": "3",
    "time_since_open": "\u6682\u65e0"
  },
  {
    "id": "803697",
    "name": "TMNT",
    "ca": "FZ1cSa63t4Ab5xoEaZdf2NbnLjAn3vduxaWRnNXpump",
    "channel": "MomentumTrackerCN",
    "timestamp": 1765269337.0,
    "mcap": "23.04K",
    "mentions": "1",
    "time_since_open": "\u6682\u65e0"
  },
  {
    "id": "803698",
    "name": "EVRO",
    "ca": "HPrF8Ba11X7FLHSqMRkeY8Snf9EZ3vT7eDbwzz41pump",
    "channel": "MomentumTrackerCN",
    "timestamp": 1765269501.0,
    "mcap": "35.06K",
    "mentions": "4",
    "time_since_open": "\u6682\u65e0"
  },
  {
    "id": "803699",
    "name": "Gru",
    "ca": "5wfSeKwi6cmHu5XTKYUgbiZtUC7TNXqRsznBmTQ8pump",
    "channel": "MomentumTrackerCN",
    "timestamp": 1765269501.0,
    "mcap": "51.68K",
    "mentions": "8",
    "time_since_open": "10\u79d2"
  },
  {
    "id": "803700",
    "name": "ICE",
    "ca": "HopGeTEbxTPyjPCriTCraaARmSaykCR9WZVx48pTzLU",
    "channel": "MomentumTrackerCN",
    "timestamp": 1765269506.0,
    "mcap": "90.58K",
    "mentions": "17",
    "time_since_open": "5\u79d2"
  },
  {
    "id": "803702",
    "name": "EVRO",
    "ca": "HPrF8Ba11X7FLHSqMRkeY8Snf9EZ3vT7eDbwzz41pump",
    "channel": "MomentumTrackerCN",
    "timestamp": 1765269576.0,
    "mcap": "45.88K",
    "mentions": "5",
    "time_since_open": "\u5c0f\u4e8e1\u5206\u949f"
  },
  {
    "id": "803703",
    "name": "EVRO",
    "ca": "HPrF8Ba11X7FLHSqMRkeY8Snf9EZ3vT7eDbwzz41pump",
    "channel": "MomentumTrackerCN",
    "timestamp": 1765269590.0,
    "mcap": "44.06K",
    "mentions": "6",
    "time_since_open": "8\u79d2"
  },
  {
    "id": "803704",
    "name": "EVRO",
    "ca": "HPrF8Ba11X7FLHSqMRkeY8Snf9EZ3vT7eDbwzz41pump",
    "channel": "MomentumTrackerCN",
    "timestamp": 1765269604.0,
    "mcap": "45.63K",
    "mentions": "7",
    "time_since_open": "8\u79d2"
  },
  {
    "id": "803706",
    "name": "EVRO",
    "ca": "HPrF8Ba11X7FLHSqMRkeY8Snf9EZ3vT7eDbwzz41pump",
    "channel": "MomentumTrackerCN",
    "timestamp": 1765269997.0,
    "mcap": "70.82K",
    "mentions": "8",
    "time_since_open": "8\u79d2"
  },
  {
    "id": "803707",
    "name": "DOB",
    "ca": "rNuSVfceNemzL5KmfpNhLx9gZS2kKNR7gZPrqN1pump",
    "channel": "MomentumTrackerCN",
    "timestamp": 1765269997.0,
    "mcap": "35.51K",
    "mentions": "1",
    "time_since_open": "12\u520623\u79d2"
  },
  {
    "id": "803708",
    "name": "EVRO",
    "ca": "HPrF8Ba11X7FLHSqMRkeY8Snf9EZ3vT7eDbwzz41pump",
    "channel": "MomentumTrackerCN",
    "timestamp": 1765269997.0,
    "mcap": "70.83K",
    "mentions": "9",
    "time_since_open": "8\u79d2"
  },
  {
    "id": "803709",
    "name": "RNUT",
    "ca": "BkEvgC9nfhy9TpCJDPUGy9ANXbYMxosfmLzk35gqpump",
    "channel": "MomentumTrackerCN",
    "timestamp": 1765269997.0,
    "mcap": "23.90K",
    "mentions": "1",
    "time_since_open": "\u6682\u65e0"
  },
  {
    "id": "803710",
    "name": "EVRO",
    "ca": "HPrF8Ba11X7FLHSqMRkeY8Snf9EZ3vT7eDbwzz41pump",
    "channel": "MomentumTrackerCN",
    "timestamp": 1765269998.0,
    "mcap": "70.83K",
    "mentions": "10",
    "time_since_open": "8\u79d2"
  },
  {
    "id": "803711",
    "name": "EVRO",
    "ca": "HPrF8Ba11X7FLHSqMRkeY8Snf9EZ3vT7eDbwzz41pump",
    "channel": "MomentumTrackerCN",
    "timestamp": 1765270004.0,
    "mcap": "70.83K",
    "mentions": "11",
    "time_since_open": "8\u79d2"
  },
  {
    "id": "803712",
    "name": "EVRO",
    "ca": "HPrF8Ba11X7FLHSqMRkeY8Snf9EZ3vT7eDbwzz41pump",
    "channel": "MomentumTrackerCN",
    "timestamp": 1765270011.0,
    "mcap": "70.85K",
    "mentions": "12",
    "time_since_open": "8\u79d2"
  },
  {
    "id": "803713",
    "name": "EVRO",
    "ca": "HPrF8Ba11X7FLHSqMRkeY8Snf9EZ3vT7eDbwzz41pump",
    "channel": "MomentumTrackerCN",
    "timestamp": 1765270084.0,
    "mcap": "82.67K",
    "mentions": "13",
    "time_since_open": "8\u79d2"
  },
  {
    "id": "803714",
    "name": "DONALD",
    "ca": "Bi1WGxZBEn3FZ1eYdxqutX5iSrK5MaVQg8wqyhnrpump",
    "channel": "MomentumTrackerCN",
    "timestamp": 1765270084.0,
    "mcap": "22.55K",
    "mentions": "1",
    "time_since_open": "\u6682\u65e0"
  },
  {
    "id": "803718",
    "name": "EVRO",
    "ca": "HPrF8Ba11X7FLHSqMRkeY8Snf9EZ3vT7eDbwzz41pump",
    "channel": "MomentumTrackerCN",
    "timestamp": 1765270316.0,
    "mcap": "78.45K",
    "mentions": "14",
    "time_since_open": "8\u79d2"
  },
  {
    "id": "803719",
    "name": "WLC",
    "ca": "97jS5yH22prinVVRBEamgV669b6ZxgWwGka2AxRmpump",
    "channel": "MomentumTrackerCN",
    "timestamp": 1765270316.0,
    "mcap": "41.14K",
    "mentions": "3",
    "time_since_open": "\u6682\u65e0"
  },
  {
    "id": "803720",
    "name": "ROCKET",
    "ca": "3o7gK8vZQV9rjPAtSVRMLPjh4xMs7MHfrcnyqxorpump",
    "channel": "MomentumTrackerCN",
    "timestamp": 1765270316.0,
    "mcap": "26.86K",
    "mentions": "1",
    "time_since_open": "\u6682\u65e0"
  },
  {
    "id": "803721",
    "name": "ACT",
    "ca": "nLu7QCUtvH6aLUb8RzkVgrB7FnUZNQrsAVeeLuLpump",
    "channel": "MomentumTrackerCN",
    "timestamp": 1765270316.0,
    "mcap": "136.88K",
    "mentions": "1",
    "time_since_open": "2\u520622\u79d2"
  },
  {
    "id": "803647",
    "name": "Petty",
    "ca": "9Rj3LqG8e2JedW2GpEqtDNVminUwfwnNi8bgUEXHpump",
    "channel": "MomentumTrackerCN",
    "timestamp": 1765267118.0,
    "mcap": "237.25K",
    "mentions": "19",
    "time_since_open": "4\u79d2"
  },
  {
    "id": "803648",
    "name": "ICE",
    "ca": "HopGeTEbxTPyjPCriTCraaARmSaykCR9WZVx48pTzLU",
    "channel": "MomentumTrackerCN",
    "timestamp": 1765267118.0,
    "mcap": "151.32K",
    "mentions": "16",
    "time_since_open": "5\u79d2"
  },
  {
    "id": "803649",
    "name": "MEMERUN",
    "ca": "1W9V5vdMAvx8Ma52TkzLTT35XQ9wtTLaJMYr8g5pump",
    "channel": "MomentumTrackerCN",
    "timestamp": 1765267119.0,
    "mcap": "3.16K",
    "mentions": "1",
    "time_since_open": "5\u79d2"
  },
  {
    "id": "803650",
    "name": "MEMERUN",
    "ca": "1W9V5vdMAvx8Ma52TkzLTT35XQ9wtTLaJMYr8g5pump",
    "channel": "MomentumTrackerCN",
    "timestamp": 1765267119.0,
    "mcap": "3.16K",
    "mentions": "2",
    "time_since_open": "5\u79d2"
  },
  {
    "id": "803651",
    "name": "MEMERUN",
    "ca": "1W9V5vdMAvx8Ma52TkzLTT35XQ9wtTLaJMYr8g5pump",
    "channel": "MomentumTrackerCN",
    "timestamp": 1765267119.0,
    "mcap": "3.16K",
    "mentions": "3",
    "time_since_open": "5\u79d2"
  },
  {
    "id": "803652",
    "name": "USDT",
    "ca": "3Expf4KgPJ2tJHoz71jZmLP6RpSbW8bCMqiNH7oepump",
    "channel": "MomentumTrackerCN",
    "timestamp": 1765267123.0,
    "mcap": "79.51K",
    "mentions": "14",
    "time_since_open": "7\u79d2"
  },
  {
    "id": "803653",
    "name": "SADGE",
    "ca": "8mCYtxU9bvXMvHwoBMjzUGSG9zAg4kgS1Bc5m4rVpump",
    "channel": "MomentumTrackerCN",
    "timestamp": 1765267123.0,
    "mcap": "37.08K",
    "mentions": "4",
    "time_since_open": "\u6682\u65e0"
  },
  {
    "id": "803654",
    "name": "SADGE",
    "ca": "8mCYtxU9bvXMvHwoBMjzUGSG9zAg4kgS1Bc5m4rVpump",
    "channel": "MomentumTrackerCN",
    "timestamp": 1765267123.0,
    "mcap": "37.08K",
    "mentions": "5",
    "time_since_open": "\u6682\u65e0"
  },
  {
    "id": "803655",
    "name": "FRC",
    "ca": "GQ3kjwiRn41Y8xBn3vVNvZpeJCQYbFFauszE3FSPpump",
    "channel": "MomentumTrackerCN",
    "timestamp": 1765267123.0,
    "mcap": "79.23K",
    "mentions": "3",
    "time_since_open": "3\u52061\u79d2"
  },
  {
    "id": "803656",
    "name": "Isabella",
    "ca": "A7bqzEeCA8Cxn3YgkGFz8bTu4QDGy2FAzDy4QXxYpump",
    "channel": "MomentumTrackerCN",
    "timestamp": 1765267123.0,
    "mcap": "20.66K",
    "mentions": "1",
    "time_since_open": "\u6682\u65e0"
  },
  {
    "id": "803659",
    "name": "Michael",
    "ca": "7dmbYPmKHkaWu4vz4Gir4se1vytRRGS3Xw8NhTefpump",
    "channel": "MomentumTrackerCN",
    "timestamp": 1765267446.0,
    "mcap": "19.08K",
    "mentions": "1",
    "time_since_open": "\u6682\u65e0"
  },
  {
    "id": "803660",
    "name": "Michael",
    "ca": "7dmbYPmKHkaWu4vz4Gir4se1vytRRGS3Xw8NhTefpump",
    "channel": "MomentumTrackerCN",
    "timestamp": 1765267447.0,
    "mcap": "19.08K",
    "mentions": "2",
    "time_since_open": "\u6682\u65e0"
  },
  {
    "id": "803661",
    "name": "ICE",
    "ca": "8nXRtx8WThtkJqSJjMxRKbqsgKiqyw1fVsj8HnvzcLMy",
    "channel": "MomentumTrackerCN",
    "timestamp": 1765267447.0,
    "mcap": "N/A",
    "mentions": "11",
    "time_since_open": "\u6682\u65e0"
  },
  {
    "id": "803663",
    "name": "ICE",
    "ca": "8nXRtx8WThtkJqSJjMxRKbqsgKiqyw1fVsj8HnvzcLMy",
    "channel": "MomentumTrackerCN",
    "timestamp": 1765267506.0,
    "mcap": "N/A",
    "mentions": "12",
    "time_since_open": "\u6682\u65e0"
  },
  {
    "id": "803664",
    "name": "SADGE",
    "ca": "8mCYtxU9bvXMvHwoBMjzUGSG9zAg4kgS1Bc5m4rVpump",
    "channel": "MomentumTrackerCN",
    "timestamp": 1765267506.0,
    "mcap": "51.03K",
    "mentions": "6",
    "time_since_open": "10\u79d2"
  },
  {
    "id": "803665",
    "name": "SADGE",
    "ca": "8mCYtxU9bvXMvHwoBMjzUGSG9zAg4kgS1Bc5m4rVpump",
    "channel": "MomentumTrackerCN",
    "timestamp": 1765267506.0,
    "mcap": "50.30K",
    "mentions": "7",
    "time_since_open": "10\u79d2"
  },
  {
    "id": "803666",
    "name": "SADGE",
    "ca": "8mCYtxU9bvXMvHwoBMjzUGSG9zAg4kgS1Bc5m4rVpump",
    "channel": "MomentumTrackerCN",
    "timestamp": 1765267529.0,
    "mcap": "52.85K",
    "mentions": "8",
    "time_since_open": "10\u79d2"
  },
  {
    "id": "803667",
    "name": "SADGE",
    "ca": "8mCYtxU9bvXMvHwoBMjzUGSG9zAg4kgS1Bc5m4rVpump",
    "channel": "MomentumTrackerCN",
    "timestamp": 1765267546.0,
    "mcap": "54.75K",
    "mentions": "9",
    "time_since_open": "10\u79d2"
  },
  {
    "id": "803668",
    "name": "bald",
    "ca": "5bzT4J12BqUZwC5vZs3KgNYpeDfyyZJn3KTrvNeLpump",
    "channel": "MomentumTrackerCN",
    "timestamp": 1765267559.0,
    "mcap": "50.20K",
    "mentions": "16",
    "time_since_open": "8\u79d2"
  },
  {
    "id": "803669",
    "name": "SADGE",
    "ca": "8mCYtxU9bvXMvHwoBMjzUGSG9zAg4kgS1Bc5m4rVpump",
    "channel": "MomentumTrackerCN",
    "timestamp": 1765267571.0,
    "mcap": "54.04K",
    "mentions": "10",
    "time_since_open": "10\u79d2"
  },
  {
    "id": "803670",
    "name": "SADGE",
    "ca": "8mCYtxU9bvXMvHwoBMjzUGSG9zAg4kgS1Bc5m4rVpump",
    "channel": "MomentumTrackerCN",
    "timestamp": 1765268471.0,
    "mcap": "60.79K",
    "mentions": "11",
    "time_since_open": "10\u79d2"
  },
  {
    "id": "803671",
    "name": "ICE",
    "ca": "8nXRtx8WThtkJqSJjMxRKbqsgKiqyw1fVsj8HnvzcLMy",
    "channel": "MomentumTrackerCN",
    "timestamp": 1765268471.0,
    "mcap": "N/A",
    "mentions": "13",
    "time_since_open": "\u6682\u65e0"
  },
  {
    "id": "803672",
    "name": "MrRain",
    "ca": "xL1muj3GrN8nF8Yq1Lhr4aYBjdZbQDkmJfvhvvzpump",
    "channel": "MomentumTrackerCN",
    "timestamp": 1765268472.0,
    "mcap": "102.73K",
    "mentions": "11",
    "time_since_open": "11\u79d2"
  },
  {
    "id": "803673",
    "name": "FCH",
    "ca": "G6ZsrQpxkroFrzRfAG2iKkSMNBJyCKQG3Y7vcx55pump",
    "channel": "MomentumTrackerCN",
    "timestamp": 1765268472.0,
    "mcap": "57.88K",
    "mentions": "1",
    "time_since_open": "5\u79d2"
  },
  {
    "id": "803674",
    "name": "FCH",
    "ca": "G6ZsrQpxkroFrzRfAG2iKkSMNBJyCKQG3Y7vcx55pump",
    "channel": "MomentumTrackerCN",
    "timestamp": 1765268472.0,
    "mcap": "57.88K",
    "mentions": "2",
    "time_since_open": "5\u79d2"
  },
  {
    "id": "803675",
    "name": "MrRain",
    "ca": "xL1muj3GrN8nF8Yq1Lhr4aYBjdZbQDkmJfvhvvzpump",
    "channel": "MomentumTrackerCN",
    "timestamp": 1765268476.0,
    "mcap": "102.73K",
    "mentions": "12",
    "time_since_open": "11\u79d2"
  },
  {
    "id": "803676",
    "name": "MrRain",
    "ca": "xL1muj3GrN8nF8Yq1Lhr4aYBjdZbQDkmJfvhvvzpump",
    "channel": "MomentumTrackerCN",
    "timestamp": 1765268477.0,
    "mcap": "102.73K",
    "mentions": "13",
    "time_since_open": "11\u79d2"
  },
  {
    "id": "803677",
    "name": "SADGE",
    "ca": "8mCYtxU9bvXMvHwoBMjzUGSG9zAg4kgS1Bc5m4rVpump",
    "channel": "MomentumTrackerCN",
    "timestamp": 1765268547.0,
    "mcap": "62.89K",
    "mentions": "12",
    "time_since_open": "10\u79d2"
  },
  {
    "id": "803678",
    "name": "Gru",
    "ca": "5wfSeKwi6cmHu5XTKYUgbiZtUC7TNXqRsznBmTQ8pump",
    "channel": "MomentumTrackerCN",
    "timestamp": 1765268547.0,
    "mcap": "29.28K",
    "mentions": "1",
    "time_since_open": "\u6682\u65e0"
  },
  {
    "id": "803679",
    "name": "SADGE",
    "ca": "8mCYtxU9bvXMvHwoBMjzUGSG9zAg4kgS1Bc5m4rVpump",
    "channel": "MomentumTrackerCN",
    "timestamp": 1765268611.0,
    "mcap": "59.39K",
    "mentions": "13",
    "time_since_open": "10\u79d2"
  },
  {
    "id": "803643",
    "name": "SADGE",
    "ca": "8mCYtxU9bvXMvHwoBMjzUGSG9zAg4kgS1Bc5m4rVpump",
    "channel": "MomentumTrackerCN",
    "timestamp": 1765266217.0,
    "mcap": "34.43K",
    "mentions": "3",
    "time_since_open": "\u6682\u65e0"
  },
  {
    "id": "803614",
    "name": "MrRain",
    "ca": "xL1muj3GrN8nF8Yq1Lhr4aYBjdZbQDkmJfvhvvzpump",
    "channel": "MomentumTrackerCN",
    "timestamp": 1765264979.0,
    "mcap": "37.53K",
    "mentions": "1",
    "time_since_open": "\u6682\u65e0"
  },
  {
    "id": "803615",
    "name": "ZORMOS",
    "ca": "9GC8YhMn4gsBsy51xfuKCAjBBQbYGspv6wMPdTBbpump",
    "channel": "MomentumTrackerCN",
    "timestamp": 1765264979.0,
    "mcap": "4.20K",
    "mentions": "1",
    "time_since_open": "\u6682\u65e0"
  },
  {
    "id": "803616",
    "name": "USDT",
    "ca": "3Expf4KgPJ2tJHoz71jZmLP6RpSbW8bCMqiNH7oepump",
    "channel": "MomentumTrackerCN",
    "timestamp": 1765264979.0,
    "mcap": "53.71K",
    "mentions": "3",
    "time_since_open": "\u5c0f\u4e8e1\u5206\u949f"
  },
  {
    "id": "803617",
    "name": "USDT",
    "ca": "3Expf4KgPJ2tJHoz71jZmLP6RpSbW8bCMqiNH7oepump",
    "channel": "MomentumTrackerCN",
    "timestamp": 1765264979.0,
    "mcap": "54.30K",
    "mentions": "4",
    "time_since_open": "7\u79d2"
  },
  {
    "id": "803618",
    "name": "USDT",
    "ca": "3Expf4KgPJ2tJHoz71jZmLP6RpSbW8bCMqiNH7oepump",
    "channel": "MomentumTrackerCN",
    "timestamp": 1765264980.0,
    "mcap": "54.30K",
    "mentions": "5",
    "time_since_open": "7\u79d2"
  },
  {
    "id": "803619",
    "name": "USDT",
    "ca": "3Expf4KgPJ2tJHoz71jZmLP6RpSbW8bCMqiNH7oepump",
    "channel": "MomentumTrackerCN",
    "timestamp": 1765264984.0,
    "mcap": "54.21K",
    "mentions": "6",
    "time_since_open": "7\u79d2"
  },
  {
    "id": "803620",
    "name": "USDT",
    "ca": "3Expf4KgPJ2tJHoz71jZmLP6RpSbW8bCMqiNH7oepump",
    "channel": "MomentumTrackerCN",
    "timestamp": 1765264984.0,
    "mcap": "54.89K",
    "mentions": "7",
    "time_since_open": "7\u79d2"
  },
  {
    "id": "803621",
    "name": "SADGE",
    "ca": "8mCYtxU9bvXMvHwoBMjzUGSG9zAg4kgS1Bc5m4rVpump",
    "channel": "MomentumTrackerCN",
    "timestamp": 1765264984.0,
    "mcap": "19.06K",
    "mentions": "1",
    "time_since_open": "\u6682\u65e0"
  },
  {
    "id": "803622",
    "name": "GLOVING",
    "ca": "mVyDwawAA6r7S9UmL7FTptXiLKEd1NLQ6G1o7UJpump",
    "channel": "MomentumTrackerCN",
    "timestamp": 1765265032.0,
    "mcap": "137.02K",
    "mentions": "5",
    "time_since_open": "6\u79d2"
  },
  {
    "id": "803623",
    "name": "USDT",
    "ca": "3Expf4KgPJ2tJHoz71jZmLP6RpSbW8bCMqiNH7oepump",
    "channel": "MomentumTrackerCN",
    "timestamp": 1765265032.0,
    "mcap": "71.65K",
    "mentions": "8",
    "time_since_open": "7\u79d2"
  },
  {
    "id": "803624",
    "name": "USDT",
    "ca": "3Expf4KgPJ2tJHoz71jZmLP6RpSbW8bCMqiNH7oepump",
    "channel": "MomentumTrackerCN",
    "timestamp": 1765265045.0,
    "mcap": "68.37K",
    "mentions": "9",
    "time_since_open": "7\u79d2"
  },
  {
    "id": "803625",
    "name": "USDT",
    "ca": "3Expf4KgPJ2tJHoz71jZmLP6RpSbW8bCMqiNH7oepump",
    "channel": "MomentumTrackerCN",
    "timestamp": 1765265055.0,
    "mcap": "74.46K",
    "mentions": "10",
    "time_since_open": "7\u79d2"
  }
]